{
  "annotations": {
    "changelogDate": "20240609160710"
  },
  "applications": ["azimuteERPSpringVueMonolith04"],
  "dto": "mapstruct",
  "entityTableName": "tb_person",
  "fields": [
    {
      "fieldName": "firstname",
      "fieldType": "String",
      "fieldValidateRules": ["required", "maxlength"],
      "fieldValidateRulesMaxlength": "50"
    },
    {
      "fieldName": "lastname",
      "fieldType": "String",
      "fieldValidateRules": ["required", "maxlength"],
      "fieldValidateRulesMaxlength": "50"
    },
    {
      "fieldName": "fullname",
      "fieldType": "String",
      "fieldValidateRules": ["maxlength"],
      "fieldValidateRulesMaxlength": "100"
    },
    {
      "fieldName": "birthDate",
      "fieldType": "LocalDate",
      "fieldValidateRules": ["required"]
    },
    {
      "fieldName": "gender",
      "fieldType": "GenderEnum",
      "fieldValidateRules": ["required"],
      "fieldValues": "MALE,FEMALE,OTHER"
    },
    {
      "fieldName": "codeBI",
      "fieldType": "String",
      "fieldValidateRules": ["maxlength"],
      "fieldValidateRulesMaxlength": "20"
    },
    {
      "fieldName": "codeNIF",
      "fieldType": "String",
      "fieldValidateRules": ["maxlength"],
      "fieldValidateRulesMaxlength": "20"
    },
    {
      "fieldName": "streetAddress",
      "fieldType": "String",
      "fieldValidateRules": ["required", "maxlength"],
      "fieldValidateRulesMaxlength": "120"
    },
    {
      "fieldName": "houseNumber",
      "fieldType": "String",
      "fieldValidateRules": ["maxlength"],
      "fieldValidateRulesMaxlength": "20"
    },
    {
      "fieldName": "locationName",
      "fieldType": "String",
      "fieldValidateRules": ["maxlength"],
      "fieldValidateRulesMaxlength": "50"
    },
    {
      "fieldName": "postalCode",
      "fieldType": "String",
      "fieldValidateRules": ["required", "maxlength"],
      "fieldValidateRulesMaxlength": "9"
    },
    {
      "fieldName": "mainEmail",
      "fieldType": "String",
      "fieldValidateRules": ["unique", "required", "maxlength", "pattern"],
      "fieldValidateRulesMaxlength": "120",
      "fieldValidateRulesPattern": "^[^@\\s]+@[^@\\s]+\\.[^@\\s]+$"
    },
    {
      "fieldName": "landPhoneNumber",
      "fieldType": "String",
      "fieldValidateRules": ["maxlength"],
      "fieldValidateRulesMaxlength": "15"
    },
    {
      "fieldName": "mobilePhoneNumber",
      "fieldType": "String",
      "fieldValidateRules": ["maxlength"],
      "fieldValidateRulesMaxlength": "15"
    },
    {
      "fieldName": "occupation",
      "fieldType": "String",
      "fieldValidateRules": ["maxlength"],
      "fieldValidateRulesMaxlength": "40"
    },
    {
      "fieldName": "preferredLanguage",
      "fieldType": "String",
      "fieldValidateRules": ["maxlength"],
      "fieldValidateRulesMaxlength": "5"
    },
    {
      "fieldName": "usernameInOAuth2",
      "fieldType": "String",
      "fieldValidateRules": ["maxlength"],
      "fieldValidateRulesMaxlength": "40"
    },
    {
      "fieldName": "userIdInOAuth2",
      "fieldType": "String",
      "fieldValidateRules": ["maxlength"],
      "fieldValidateRulesMaxlength": "80"
    },
    {
      "fieldName": "customAttributesDetailsJSON",
      "fieldType": "String",
      "fieldValidateRules": ["maxlength"],
      "fieldValidateRulesMaxlength": "2048"
    },
    {
      "fieldName": "activationStatus",
      "fieldType": "ActivationStatusEnum",
      "fieldValidateRules": ["required"],
      "fieldValues": "INACTIVE,ACTIVE,ON_HOLD,PENDENT,BLOCKED,INVALID"
    },
    {
      "fieldName": "avatarImg",
      "fieldType": "byte[]",
      "fieldTypeBlobContent": "image"
    }
  ],
  "name": "Person",
  "pagination": "pagination",
  "relationships": [
    {
      "otherEntityField": "code",
      "otherEntityName": "typeOfPerson",
      "otherEntityRelationshipName": "personsList",
      "relationshipName": "typeOfPerson",
      "relationshipSide": "left",
      "relationshipType": "many-to-one",
      "relationshipValidateRules": "required"
    },
    {
      "otherEntityField": "name",
      "otherEntityName": "district",
      "otherEntityRelationshipName": "personsList",
      "relationshipName": "district",
      "relationshipSide": "left",
      "relationshipType": "many-to-one"
    },
    {
      "otherEntityField": "lastname",
      "otherEntityName": "person",
      "otherEntityRelationshipName": "managedPersonsList",
      "relationshipName": "managerPerson",
      "relationshipSide": "left",
      "relationshipType": "many-to-one"
    },
    {
      "otherEntityName": "person",
      "otherEntityRelationshipName": "managerPerson",
      "relationshipName": "managedPersonsList",
      "relationshipSide": "right",
      "relationshipType": "one-to-many"
    },
    {
      "otherEntityName": "organizationMembership",
      "otherEntityRelationshipName": "person",
      "relationshipName": "organizationMembershipsList",
      "relationshipSide": "right",
      "relationshipType": "one-to-many"
    },
    {
      "otherEntityName": "supplier",
      "otherEntityRelationshipName": "representativePerson",
      "relationshipName": "suppliersList",
      "relationshipSide": "right",
      "relationshipType": "one-to-many"
    },
    {
      "otherEntityName": "customer",
      "otherEntityRelationshipName": "buyerPerson",
      "relationshipName": "customersList",
      "relationshipSide": "right",
      "relationshipType": "one-to-many"
    },
    {
      "otherEntityName": "activity",
      "otherEntityRelationshipName": "createdByUser",
      "relationshipName": "activitiesList",
      "relationshipSide": "right",
      "relationshipType": "one-to-many"
    },
    {
      "otherEntityName": "event",
      "otherEntityRelationshipName": "promoteurPerson",
      "relationshipName": "promotedEventsList",
      "relationshipSide": "right",
      "relationshipType": "one-to-many"
    },
    {
      "otherEntityName": "eventProgram",
      "otherEntityRelationshipName": "responsiblePerson",
      "relationshipName": "eventsProgramsList",
      "relationshipSide": "right",
      "relationshipType": "one-to-many"
    },
    {
      "otherEntityName": "scheduledActivity",
      "otherEntityRelationshipName": "responsiblePerson",
      "relationshipName": "scheduledActivitiesList",
      "relationshipSide": "right",
      "relationshipType": "one-to-many"
    },
    {
      "otherEntityName": "eventAttendee",
      "otherEntityRelationshipName": "attendeePerson",
      "relationshipName": "eventAttendeesList",
      "relationshipSide": "right",
      "relationshipType": "one-to-many"
    }
  ],
  "searchEngine": "no",
  "service": "serviceImpl"
}
